Metadata-Version: 2.1
Name: prodglob
Version: 0.0.3
Summary: Lightweight glob extensions with extended path joining.
Home-page: https://github.com/beasteers/prodglob
Author: Bea Steers
Author-email: bea.steers@gmail.com
License: MIT License
Keywords: glob product os.path.join join file sort make
Platform: UNKNOWN
